ubuntu_deployer/__init__.py
ubuntu_deployer/exceptions.py
ubuntu_deployer/utils.py
ubuntu_deployer/configs/gunicorn_config.txt
ubuntu_deployer/configs/nginx_config.txt
ubuntu_deployer/management/__init__.py
ubuntu_deployer/management/commands/__init__.py
ubuntu_deployer/management/commands/deploy.py
django_ubuntu_deployer-4.3.0.dist-info/LICENSE
django_ubuntu_deployer-4.3.0.dist-info/METADATA
django_ubuntu_deployer-4.3.0.dist-info/WHEEL
django_ubuntu_deployer-4.3.0.dist-info/top_level.txt
django_ubuntu_deployer-4.3.0.dist-info/RECORD
