Metadata-Version: 2.1
Name: django-ubuntu-deployer
Version: 4.3.0
Summary: Simple way to deploy Django app in Ubuntu Server.
Home-page: https://github.com/Maksych/django_ubuntu_deployer
Author: Maksym Sichkaruk
Author-email: maxim.18.08.1997@gmail.com
License: MIT
Platform: UNKNOWN
